alu.v

module alu(A,B,out,op);
  input [7:0] A,B;
  input [2:0] op;
  output reg [7:0] out;
  always @(*)
    begin
      case(op)
        3'd0:out=A+B;
        3'd1:out=A-B;
        3'd2:out=A*B;
        3'd3:out=A/B;
        3'd4:out=A|B;
        3'd5:out=A&B;
        3'd6:out=~A;
        3'd7:out=A^B;
        default:out=0;
      endcase
    end
endmodule

alu_tb.v
//testbench here
module alu_tb;
  reg [7:0] A,B; //inputs
  reg [2:0] op; //instructions/opcodes
  wire [7:0] out; //outpus
  alu a1(A,B,out,op);
  
  integer i;
  
  initial
    begin
      A=50;B=10;op=0;
      $monitor($time,"A=%d,B=%d,op=%d,out=%d",A,B,op,out); 
      $dumpfile("alu_behavioral.vcd"); 
      $dumpvars(0,alu_tb);
      for(i=1;i<8;i=i+1)
        begin
          #10
          op=i;
          
        end
      #10 $finish();
    end
endmodule

alu_behavioral.vcd
$date
	Sun Jul 21 14:02:59 2024
$end
$version
	Icarus Verilog
$end
$timescale
	1s
$end
$scope module alu_tb $end
$var wire 8 ! out [7:0] $end
$var reg 8 " A [7:0] $end
$var reg 8 # B [7:0] $end
$var integer 32 $ i [31:0] $end
$var reg 3 % op [2:0] $end
$scope module a1 $end
$var wire 8 & A [7:0] $end
$var wire 8 ' B [7:0] $end
$var wire 3 ( op [2:0] $end
$var reg 8 ) out [7:0] $end
$upscope $end
$upscope $end
$enddefinitions $end
#0
$dumpvars
b111100 )
b0 (
b1010 '
b110010 &
b0 %
b1 $
b1010 #
b110010 "
b111100 !
$end
#10
b101000 )
b101000 !
b10 $
b1 %
b1 (
#20
b11110100 )
b11110100 !
b11 $
b10 %
b10 (
#30
b101 )
b101 !
b100 $
b11 %
b11 (
#40
b111010 )
b111010 !
b101 $
b100 %
b100 (
#50
b10 )
b10 !
b110 $
b101 %
b101 (
#60
b11001101 )
b11001101 !
b111 $
b110 %
b110 (
#70
b111000 )
b111000 !
b1000 $
b111 %
b111 (
